journal_dates.py
journal_dates-0.1.1.dist-info/DESCRIPTION.rst
journal_dates-0.1.1.dist-info/METADATA
journal_dates-0.1.1.dist-info/RECORD
journal_dates-0.1.1.dist-info/WHEEL
journal_dates-0.1.1.dist-info/entry_points.txt
journal_dates-0.1.1.dist-info/metadata.json
journal_dates-0.1.1.dist-info/top_level.txt
