Metadata-Version: 2.0
Name: journal-dates
Version: 0.1.1
Summary: Prints a monthly journal template
Home-page: http://github.com/bzamecnik/journal_dates
Author: Bohumir Zamecnik
Author-email: bohumir.zamecnik@gmail.com
License: MIT
Platform: UNKNOWN
Classifier: Development Status :: 3 - Alpha
Classifier: Topic :: Utilities
Classifier: License :: OSI Approved :: MIT License
Classifier: Programming Language :: Python :: 2
Classifier: Programming Language :: Python :: 3
Classifier: Operating System :: POSIX :: Linux
Classifier: Operating System :: MacOS :: MacOS X
Requires-Dist: arrow
